asciimol/__init__.py
asciimol/__main__.py
asciimol/app/__init__.py
asciimol/app/asciimol.py
asciimol/app/colors.py
asciimol/app/config.py
asciimol/app/io.py
asciimol/app/renderer.py
asciimol/app/data/atom_data
asciimol-1.2.3.dist-info/LICENSE
asciimol-1.2.3.dist-info/METADATA
asciimol-1.2.3.dist-info/WHEEL
asciimol-1.2.3.dist-info/entry_points.txt
asciimol-1.2.3.dist-info/top_level.txt
asciimol-1.2.3.dist-info/RECORD
