Metadata-Version: 2.1
Name: asciimol
Version: 1.2.3
Summary: An ASCII molecule viewer.
Home-page: https://github.com/dewberryants/asciimol
Author: Dominik Behrens
Author-email: dewberryants@gmail.com
License: BSD 2-Clause License
Classifier: Programming Language :: Python :: 3
Classifier: License :: OSI Approved :: BSD License
Classifier: Operating System :: OS Independent
Classifier: Topic :: Scientific/Engineering :: Chemistry
License-File: LICENSE
Requires-Dist: numpy
Provides-Extra: formats
Requires-Dist: ase ; extra == 'formats'
Provides-Extra: smiles
Requires-Dist: rdkit-pypi ; extra == 'smiles'
